egyptian/Parser.py
egyptian/Randomizer.py
egyptian/__init__.py
egyptian/db.py
egyptian/generators.py
egyptian-1.0.1.dist-info/METADATA
egyptian-1.0.1.dist-info/WHEEL
egyptian-1.0.1.dist-info/top_level.txt
egyptian-1.0.1.dist-info/RECORD
