Metadata-Version: 2.2
Name: egyptian
Version: 1.0.1
Summary: Generate Random Egyptian Information
Author-email: Mahmoud Gamal <mahmoudgshaker2018@gmail.com>
License: MIT
Project-URL: Repository, https://github.com/MahmoudGShake/egyptian.git
Requires-Dist: setuptools
